netrng/__init__.py
netrng/core.py
netrng/daemon.py
netrng/entropycheck.py
netrng/perftest.py
netrng-0.2b1.data/data/conf/netrng.conf.sample
netrng-0.2b1.data/data/conf/netrng.conf.upstart
netrng-0.2b1.data/data/conf/netrng.service
netrng-0.2b1.dist-info/DESCRIPTION.rst
netrng-0.2b1.dist-info/METADATA
netrng-0.2b1.dist-info/RECORD
netrng-0.2b1.dist-info/WHEEL
netrng-0.2b1.dist-info/entry_points.txt
netrng-0.2b1.dist-info/metadata.json
netrng-0.2b1.dist-info/top_level.txt
