Metadata-Version: 2.0
Name: netrng
Version: 0.2b1
Summary: A network entropy distribution system
Home-page: http://infincia.github.io/netrng/
Author: Stephen Oliver
Author-email: steve@infincia.com
License: MIT
Keywords: rng hwrng entropy random
Platform: any
Classifier: Development Status :: 4 - Beta
Classifier: License :: OSI Approved :: MIT License
Classifier: Natural Language :: English
Classifier: Operating System :: POSIX
Classifier: Programming Language :: Python :: 2.7
Classifier: Programming Language :: Python :: 3.2
Classifier: Programming Language :: Python :: 3.3
Classifier: Programming Language :: Python :: 3.4
Classifier: Programming Language :: Python :: 3.5
Classifier: Topic :: Software Development :: Libraries
Classifier: Topic :: Software Development :: Libraries :: Python Modules
Requires-Dist: gevent (==1.1rc1)
Requires-Dist: msgpack-python (==0.4.6)
Requires-Dist: six (==1.10.0)
Requires-Dist: zeroconf (==0.17.4)
